{
  "game_id": "2025_CFB_Georgia_Southern_Eagles_Arkansas_State_Red_Wolves",
  "teams": "Georgia Southern Eagles @ Arkansas State Red Wolves",
  "narrative_signals": [
    {
      "type": "MEDIA_DARLING",
      "strength": 0.6666666666666666,
      "source": "youtube+reddit",
      "description": "Media over-hyping - Reddit storylines: Coaching Hot Seat, Playoff Implications"
    },
    {
      "type": "SHARP_VS_PUBLIC",
      "strength": 0.475,
      "source": "betting_data",
      "description": "Sharp money on Georgia Southern Eagles"
    }
  ],
  "betting_recommendation": {
    "recommendation": "FADE_PUBLIC",
    "confidence": 0.3333333333333333,
    "signals_detected": 2,
    "dominant_narratives": [
      "MEDIA_DARLING",
      "SHARP_VS_PUBLIC"
    ],
    "reasoning": "Detected 2 narrative signals pointing to fade_public",
    "pick": "FADE PUBLIC (likely UNDER 59.5 or DOG +1.5)"
  },
  "conspiracy_probability": 1.0,
  "analysis_timestamp": "2025-10-25T17:18:23.429487"
}