{
  "game_id": "2025_CFB_Alabama_Crimson_Tide_South_Carolina_Gamecocks",
  "teams": "Alabama Crimson Tide @ South Carolina Gamecocks",
  "narrative_signals": [
    {
      "type": "SHARP_VS_PUBLIC",
      "strength": 0.55,
      "source": "betting_data",
      "description": "Sharp money on South Carolina Gamecocks"
    }
  ],
  "betting_recommendation": {
    "recommendation": "FOLLOW_SHARP",
    "confidence": 0.55,
    "signals_detected": 1,
    "dominant_narratives": [
      "SHARP_VS_PUBLIC"
    ],
    "reasoning": "Detected 1 narrative signals pointing to follow_sharp",
    "pick": "DOG +16.5 (sharp fade)"
  },
  "conspiracy_probability": 0.4675,
  "analysis_timestamp": "2025-10-25T17:18:15.428893"
}